win32fastutils/__init__.py
win32fastutils/consoleutils.py
win32fastutils/guiutils.py
win32fastutils/py32fix.py
win32fastutils-0.1.1.dist-info/LICENSE
win32fastutils-0.1.1.dist-info/METADATA
win32fastutils-0.1.1.dist-info/WHEEL
win32fastutils-0.1.1.dist-info/top_level.txt
win32fastutils-0.1.1.dist-info/RECORD
